{
  "neoforge:conditions": [
    {
      "type": "neoforge:not",
      "value": {
        "type": "neoforge:tag_empty",
        "tag": "c:gems/ruby"
      }
    },
    {
      "type": "neoforge:not",
      "value": {
        "type": "neoforge:tag_empty",
        "tag": "c:gems/ruby"
      }
    }
  ],
  "type": "theurgy:reformation",
  "category": "misc",
  "mercuryFlux": 150,
  "result": {
    "type": "theurgy:item",
    "count": 1,
    "id": "theurgy:alchemical_sulfur_ruby"
  },
  "sources": [
    {
      "count": 1,
      "item": "theurgy:alchemical_niter_gems_rare"
    }
  ],
  "target": {
    "item": "theurgy:alchemical_sulfur_ruby"
  },
  "time": 100
}