{
  "multipart": [
    {
      "apply": {
        "model": "theurgy:block/incubator"
      }
    },
    {
      "apply": {
        "model": "theurgy:block/incubator_pipe",
        "uvlock": true
      },
      "when": {
        "north": "true"
      }
    },
    {
      "apply": {
        "model": "theurgy:block/incubator_pipe",
        "uvlock": true,
        "y": 180
      },
      "when": {
        "south": "true"
      }
    },
    {
      "apply": {
        "model": "theurgy:block/incubator_pipe",
        "uvlock": true,
        "y": 270
      },
      "when": {
        "west": "true"
      }
    },
    {
      "apply": {
        "model": "theurgy:block/incubator_pipe",
        "uvlock": true,
        "y": 90
      },
      "when": {
        "east": "true"
      }
    }
  ]
}