{
  "neoforge:conditions": [
    {
      "type": "neoforge:not",
      "value": {
        "type": "neoforge:tag_empty",
        "tag": "c:ores/gold"
      }
    }
  ],
  "type": "theurgy:liquefaction",
  "category": "misc",
  "ingredient": {
    "tag": "c:ores/gold"
  },
  "result": {
    "count": 5,
    "item": "theurgy:alchemical_sulfur_gold",
    "nbt": {
      "theurgy:sulfur.source.id": "#c:ores/gold"
    }
  },
  "solvent": {
    "fluid": "theurgy:sal_ammoniac"
  },
  "solvent_amount": 15,
  "time": 100
}