{
  "type": "theurgy:liquefaction",
  "conditions": [
    {
      "type": "forge:not",
      "value": {
        "type": "forge:tag_empty",
        "tag": "forge:ores/sal_ammoniac"
      }
    }
  ],
  "ingredient": {
    "tag": "forge:ores/sal_ammoniac"
  },
  "liquefaction_time": 100,
  "result": {
    "count": 6,
    "item": "theurgy:alchemical_sulfur_sal_ammoniac",
    "nbt": {
      "theurgy:sulfur.source.id": "#forge:ores/sal_ammoniac"
    }
  },
  "solvent": {
    "fluid": "theurgy:sal_ammoniac"
  },
  "solvent_amount": 15
}